gnar_gear/__init__.py
gnar_gear/constants.py
gnar_gear/gnar_app.py
gnar_gear-1.1.5.dist-info/METADATA
gnar_gear-1.1.5.dist-info/RECORD
gnar_gear-1.1.5.dist-info/WHEEL
gnar_gear-1.1.5.dist-info/top_level.txt
gnar_gear-1.1.5.dist-info/zip-safe
