Metadata-Version: 2.1
Name: gnar-gear
Version: 1.1.5
Summary: The gnarliest gear in the world 🤙
Home-page: https://gitlab.com/gnaar/gear
Author: Brien R. Givens
Author-email: ic3b3rg@gmail.com
License: MIT
Platform: UNKNOWN
Classifier: Development Status :: 5 - Production/Stable
Classifier: Intended Audience :: Developers
Classifier: Natural Language :: English
Classifier: License :: OSI Approved :: MIT License
Classifier: Programming Language :: Python
Classifier: Programming Language :: Python :: 3
Classifier: Programming Language :: Python :: 3.5
Classifier: Programming Language :: Python :: 3.6
Classifier: Programming Language :: Python :: 3.7
Classifier: Framework :: Flask
Requires-Dist: argon2-cffi (>=18.3.0)
Requires-Dist: boto3 (>=1.9.75)
Requires-Dist: bjoern (>=2.2.3)
Requires-Dist: flask (>=1.0.2)
Requires-Dist: flask-jwt-extended (>=3.15.0)
Requires-Dist: postgres (>=2.2.2)
Requires-Dist: requests (>=2.21.0)
